precise_money
