Metadata-Version: 2.1
Name: precise_money
Version: 0.1.3
Summary: A Python library for handling monetary values and currencies with maniacal attention to precision. PreciseMoney offers robust tools for financial calculations and currency management, ensuring accuracy in even the most complex monetary operations. Perfect for developers who lose sleep over floating-point errors.
Home-page: https://github.com/ListfulAl/PreciseMoney
Author: Cathleen Turner
Author-email: cathleen.turner@autaly.co
Classifier: Programming Language :: Python :: 3
Classifier: Programming Language :: Python :: 3.10
Classifier: License :: OSI Approved :: MIT License
Classifier: Operating System :: OS Independent
Requires-Python: >=3.10
License-File: LICENSE
Requires-Dist: pydantic-core>=2.23.0
Provides-Extra: dev
Requires-Dist: pytest; extra == "dev"
Requires-Dist: twine; extra == "dev"
Requires-Dist: pydantic; extra == "dev"
